<annotation verified="yes">
	<folder>cup_cakes</folder>
	<filename>3209445.jpg</filename>
	<path>C:\Users\KristianW\Bangkit\Capstone\Food-Detection-w-Machine-Learning\train\cup_cakes\3209445.jpg</path>
	<source>
		<database>Unknown</database>
	</source>
	<size>
		<width>512</width>
		<height>512</height>
		<depth>3</depth>
	</size>
	<segmented>0</segmented>
	<object>
		<name>cup_cakes</name>
		<pose>Unspecified</pose>
		<truncated>0</truncated>
		<difficult>0</difficult>
		<bndbox>
			<xmin>56</xmin>
			<ymin>6</ymin>
			<xmax>436</xmax>
			<ymax>495</ymax>
		</bndbox>
	</object>
</annotation>
