<annotation>
	<folder>ayam_geprek</folder>
	<filename>images519.jpg</filename>
	<path>C:\Users\KristianW\Bangkit\Capstone\Food-Detection-w-Machine-Learning\train\ayam_geprek\images519.jpg</path>
	<source>
		<database>Unknown</database>
	</source>
	<size>
		<width>205</width>
		<height>245</height>
		<depth>3</depth>
	</size>
	<segmented>0</segmented>
	<object>
		<name>ayam_geprek</name>
		<pose>Unspecified</pose>
		<truncated>0</truncated>
		<difficult>0</difficult>
		<bndbox>
			<xmin>7</xmin>
			<ymin>103</ymin>
			<xmax>202</xmax>
			<ymax>242</ymax>
		</bndbox>
	</object>
</annotation>
