<annotation>
	<folder>ayam_geprek</folder>
	<filename>images407.jpg</filename>
	<path>C:\Users\KristianW\Bangkit\Capstone\Food-Detection-w-Machine-Learning\train\ayam_geprek\images407.jpg</path>
	<source>
		<database>Unknown</database>
	</source>
	<size>
		<width>270</width>
		<height>187</height>
		<depth>3</depth>
	</size>
	<segmented>0</segmented>
	<object>
		<name>ayam_geprek</name>
		<pose>Unspecified</pose>
		<truncated>0</truncated>
		<difficult>0</difficult>
		<bndbox>
			<xmin>30</xmin>
			<ymin>12</ymin>
			<xmax>245</xmax>
			<ymax>175</ymax>
		</bndbox>
	</object>
</annotation>
