<annotation verified="yes">
	<folder>hamburger</folder>
	<filename>3568995.jpg</filename>
	<path>C:\Users\KristianW\Bangkit\Capstone\Food-Detection-w-Machine-Learning\train\hamburger\3568995.jpg</path>
	<source>
		<database>Unknown</database>
	</source>
	<size>
		<width>512</width>
		<height>382</height>
		<depth>3</depth>
	</size>
	<segmented>0</segmented>
	<object>
		<name>hamburger</name>
		<pose>Unspecified</pose>
		<truncated>0</truncated>
		<difficult>0</difficult>
		<bndbox>
			<xmin>190</xmin>
			<ymin>76</ymin>
			<xmax>427</xmax>
			<ymax>330</ymax>
		</bndbox>
	</object>
</annotation>
