<annotation>
	<folder>pizza</folder>
	<filename>image.jpg</filename>
	<path>E:\KULIAH\SEMESTER 8\Program Bangkit\Proyek\Food-Detection-w-Machine-Learning\train\pizza\image.jpg</path>
	<source>
		<database>Unknown</database>
	</source>
	<size>
		<width>2000</width>
		<height>999</height>
		<depth>3</depth>
	</size>
	<segmented>0</segmented>
	<object>
		<name>pizza</name>
		<pose>Unspecified</pose>
		<truncated>1</truncated>
		<difficult>0</difficult>
		<bndbox>
			<xmin>8</xmin>
			<ymin>3</ymin>
			<xmax>1548</xmax>
			<ymax>999</ymax>
		</bndbox>
	</object>
</annotation>
