<annotation>
	<folder>prime_rib</folder>
	<filename>3012205.jpg</filename>
	<path>E:\KULIAH\SEMESTER 8\Program Bangkit\Proyek\Food-Detection-w-Machine-Learning\train\prime_rib\3012205.jpg</path>
	<source>
		<database>Unknown</database>
	</source>
	<size>
		<width>512</width>
		<height>384</height>
		<depth>3</depth>
	</size>
	<segmented>0</segmented>
	<object>
		<name>prime_rib</name>
		<pose>Unspecified</pose>
		<truncated>1</truncated>
		<difficult>0</difficult>
		<bndbox>
			<xmin>10</xmin>
			<ymin>20</ymin>
			<xmax>512</xmax>
			<ymax>328</ymax>
		</bndbox>
	</object>
</annotation>
